deepglue/__init__.py
deepglue/environment_utils.py
deepglue/file_utils.py
deepglue/plot_utils.py
deepglue/training_utils.py
deepglue-0.1.14.dist-info/METADATA
deepglue-0.1.14.dist-info/WHEEL
deepglue-0.1.14.dist-info/licenses/LICENSE
deepglue-0.1.14.dist-info/RECORD
